src/IEEE488.py
src/Instrument.py
src/SCPI.py
src/__about__.py
src/__init__.py
src/Attenuator/MI2187.py
src/AudioAnalyser/HP8903B.py
src/AudioAnalyser/RaSCMU200Audio.py
src/Controller/amplitude.py
src/Controller/frequency.py
src/Controller/modulation.py
src/DigitalMultimeter/HP34401A.py
src/DigitalMultimeter/TP4000ZC.py
src/DigitalMultimeter/hp34401A.md
src/Enviromental/HeraeusVotschVMT04.py
src/Enviromental/hydrotherm.py
src/FieldStrength/EMC 20 Emulator.py
src/FieldStrength/EMC 20 Reader.py
src/FieldStrength/EMC20.py
src/FieldStrength/LumiloopLSProbe.py
src/FieldStrength/Narda601.py
src/File/snp.py
src/File/wv.py
src/FilterRF/AgilentN9039A.py
src/Formatter/plot.py
src/Formula/Audio.py
src/Formula/IQ.py
src/Formula/RI.py
src/Formula/Units.py
src/FrequencyCounter/FrequencyCounter.py
src/FrequencyCounter/HP53132A.py
src/FrequencyCounter/IFRCPM47.py
src/FrequencyCounter/Racal1992.py
src/ModulationMeter/HP8901B.py
src/ModulationMeter/MI2305.py
src/NetworkAnalyser/AgilentE8357A.py
src/NetworkAnalyser/AnritsuShockline.py
src/NetworkAnalyser/HP4395A.py
src/NetworkAnalyser/KeysightFieldFox.py
src/NetworkAnalyser/Wiltron360.py
src/Oscilloscope/KeysightInfiniiVisionX.py
src/Oscilloscope/TektronixTDS7104.py
src/PATester/SeawardPAT.py
src/Positioner/AnaheimAutomationSMC40.py
src/Positioner/ETS2090.py
src/PowerAnalyser/VoltechPM100.py
src/PowerAnalyser/VoltechPM1000P.py
src/PowerAnalyser/VoltechPM3000A.py
src/PowerMeter/AgilentE4418B.py
src/PowerMeter/ELVA1DPM.py
src/PowerMeter/HP437B.py
src/PowerMeter/MI6960.py
src/PowerMeter/RohdeSchwarzNRVS.py
src/PowerMeter/VDIPM5B.py
src/PowerSourceAC/SourceAC.py
src/PowerSourceDC/AgilentN7972A.py
src/PowerSourceDC/HP59501B.py
src/PowerSourceDC/HP6632A.py
src/PowerSourceDC/HP6674A.py
src/PowerSourceDC/TTIPL303.py
src/PowerSourceDC/TTIPL330P.py
src/RangeFinder/ArduinoLIDAR.py
src/SignalGenerator/Agilent83650B.py
src/SignalGenerator/AgilentE4422B.py
src/SignalGenerator/AgilentE4438C.py
src/SignalGenerator/AgilentN5181A.py
labtoolkit-1.4.0.dist-info/METADATA
labtoolkit-1.4.0.dist-info/WHEEL
labtoolkit-1.4.0.dist-info/licenses/LICENSE
labtoolkit-1.4.0.dist-info/RECORD
