Metadata-Version: 2.1
Name: LabToolkit
Version: 1.4.0
Summary: Python package for instrument control, data acquisition and automation
Project-URL: Homepage, https://github.com/DavidLutton/LabToolkit
Project-URL: Issues, https://github.com/DavidLutton/LabToolkit/issues
Author-email: David Lutton <david.lutton@gmail.com>
License-File: LICENSE
Keywords: Acquisition,GPIB,Measurement,RS232,Serial,USB,VISA
Classifier: Development Status :: 4 - Beta
Classifier: Intended Audience :: Developers
Classifier: License :: OSI Approved :: MIT License
Classifier: Natural Language :: English
Classifier: Operating System :: OS Independent
Classifier: Programming Language :: Python :: 3
Classifier: Programming Language :: Python :: 3.10
Classifier: Programming Language :: Python :: 3.11
Classifier: Programming Language :: Python :: 3.12
Requires-Python: >=3.10
Requires-Dist: numpy
Requires-Dist: pandas
Requires-Dist: pyvisa
Provides-Extra: screenshots
Requires-Dist: pillow; extra == 'screenshots'
Provides-Extra: vxi11
Requires-Dist: pyvisa-py; extra == 'vxi11'
